README.md
setup.py
sanic_asyncjinja2/__init__.py
sanic_asyncjinja2/asyncjinja2.py
sanic_asyncjinja2.egg-info/PKG-INFO
sanic_asyncjinja2.egg-info/SOURCES.txt
sanic_asyncjinja2.egg-info/dependency_links.txt
sanic_asyncjinja2.egg-info/not-zip-safe
sanic_asyncjinja2.egg-info/requires.txt
sanic_asyncjinja2.egg-info/top_level.txt