Metadata-Version: 2.1
Name: sanic-asyncjinja2
Version: 0.1.2
Summary: Sanic integration with Jinja2 in async mode [experimental]
Home-page: https://github.com/EndurantDevs/sanic-asyncjinja2
Author: Endurant Devs
Author-email: info@endurantdevs.com
License: MIT
Keywords: sanic-asyncjinja2 sanic jinja2 template
Platform: UNKNOWN
Classifier: Intended Audience :: Developers
Classifier: Environment :: Web Environment
Classifier: License :: OSI Approved :: MIT License
Classifier: Natural Language :: English
Classifier: Programming Language :: Python :: 3
Classifier: Programming Language :: Python :: 3.6
Classifier: Programming Language :: Python :: 3.7
